airflow_providers_rdb_to_rdb/PostgresToTiDBOperator.py
airflow_providers_rdb_to_rdb/__init__.py
airflow_providers_rdb_to_rdb-1.0.2.dist-info/METADATA
airflow_providers_rdb_to_rdb-1.0.2.dist-info/WHEEL
airflow_providers_rdb_to_rdb-1.0.2.dist-info/top_level.txt
airflow_providers_rdb_to_rdb-1.0.2.dist-info/RECORD
